{
    "m_Version": 12,
    "DisplayName": "Maschienengewehre",
    "Icon": "Deliver",
    "Color": "FBFCFEFF",
    "IsExchange": 0,
    "InitStockPercent": 75.0,
    "Items": [
        {
            "ClassName": "GCGN_M249",
            "MaxPriceThreshold": 185000,
            "MinPriceThreshold": 185000,
            "SellPricePercent": 20,
            "MaxStockThreshold": 1,
            "MinStockThreshold": 1,
            "QuantityPercent": 0,
            "SpawnAttachments": [],
            "Variants": []
        },
        {
            "ClassName": "SNAFURPD",
            "MaxPriceThreshold": 185000,
            "MinPriceThreshold": 185000,
            "SellPricePercent": 20,
            "MaxStockThreshold": 1,
            "MinStockThreshold": 1,
            "QuantityPercent": 0,
            "SpawnAttachments": [],
            "Variants": []
        },
        {
            "ClassName": "Snafu_pkp_NBlack_GUN",
            "MaxPriceThreshold": 185000,
            "MinPriceThreshold": 185000,
            "SellPricePercent": 20,
            "MaxStockThreshold": 1,
            "MinStockThreshold": 1,
            "QuantityPercent": 0,
            "SpawnAttachments": [],
            "Variants": []
        },
        {
            "ClassName": "SNAFU_U100",
            "MaxPriceThreshold": 150000,
            "MinPriceThreshold": 150000,
            "SellPricePercent": -1.0,
            "MaxStockThreshold": 5,
            "MinStockThreshold": 1,
            "QuantityPercent": 0,
            "SpawnAttachments": [],
            "Variants": []
        }
    ]
}